codex_processor/__init__.py
codex_processor/__main__.py
codex_processor/codex_processor.py
codex_processor/converter.py
codex_processor/install.py
codex_processor/template_processor.py
codex_processor/typograph.py
codex_processor/utils.py
codex_processor/version.py
codex_processor/wrapper.py
codex_processor/resources/latex_source.json
codex_processor/resources/template.docx
codex_processor/resources/template.tex
codex_processor-0.0.14.dist-info/LICENSE.md
codex_processor-0.0.14.dist-info/METADATA
codex_processor-0.0.14.dist-info/WHEEL
codex_processor-0.0.14.dist-info/entry_points.txt
codex_processor-0.0.14.dist-info/top_level.txt
codex_processor-0.0.14.dist-info/RECORD
